{
  "model_ports": {
    "manager": 8001,
    "language": 8002,
    "audio": 8003,
    "vision_image": 8004,
    "vision_video": 8005,
    "spatial": 8006,
    "sensor": 8007,
    "computer": 8008,
    "motion": 8009,
    "knowledge": 8010,
    "programming": 8011,
    "emotion": 8012,
    "finance": 8013,
    "medical": 8014,
    "planning": 8015,
    "prediction": 8016,
    "collaboration": 8017,
    "optimization": 8018,
    "autonomous": 8019
  },
  "main_api": {
    "port": 8000,
    "host": "0.0.0.0",
    "workers": 1
  },
  "realtime_stream_manager": {
    "port": 8765,
    "host": "0.0.0.0"
  },
  "service_settings": {
    "auto_start": true,
    "max_workers": 5,
    "health_check_interval": 30,
    "timeout": 10,
    "retry_count": 3
  },
  "logging": {
    "level": "INFO",
    "file_path": "logs/model_services.log",
    "rotation": "1 day",
    "retention": "7 days"
  },
  "performance_monitoring": {
    "enabled": true,
    "metrics_port": 8081,
    "collection_interval": 15
  },
  "hardware_config": {
    "camera_settings": {
      "max_cameras": 4,
      "default_resolution": "1280x720",
      "supported_interfaces": ["usb", "ethernet", "csi"],
      "frame_rate": 30,
      "auto_detect": true
    },
    "sensor_settings": {
      "supported_sensors": [
        "temperature",
        "humidity", 
        "accelerometer",
        "gyroscope",
        "pressure",
        "distance",
        "infrared",
        "light",
        "smoke"
      ],
      "polling_interval": 1000,
      "data_format": "json"
    },
    "actuator_settings": {
      "supported_protocols": ["uart", "i2c", "spi", "pwm"],
      "default_baud_rate": 9600,
      "timeout_ms": 5000
    },
    "communication_settings": {
      "max_retries": 3,
      "retry_delay_ms": 100,
      "connection_timeout_ms": 10000
    }
  }
}
